cache_house/__init__.py
cache_house/backends/__init__.py
cache_house/backends/redis_backend.py
cache_house/backends/redis_cluster_backend.py
cache_house/cache.py
cache_house/exceptions.py
cache_house/helpers.py
cache_house-1.0.1.dist-info/METADATA
cache_house-1.0.1.dist-info/WHEEL
cache_house-1.0.1.dist-info/licenses/LICENCE.md
cache_house-1.0.1.dist-info/RECORD
