Metadata-Version: 2.4
Name: cache_house
Version: 1.0.1
Summary: Caching tool for python
License: MIT
License-File: LICENCE.md
Author: Tural Muradov
Author-email: tural_m@hotmail.com
Requires-Python: >=3.10,<4.0
Classifier: License :: OSI Approved :: MIT License
Classifier: Programming Language :: Python :: 3
Classifier: Programming Language :: Python :: 3.10
Classifier: Programming Language :: Python :: 3.11
Classifier: Programming Language :: Python :: 3.12
Classifier: Programming Language :: Python :: 3.13
Classifier: Programming Language :: Python :: 3.14
Requires-Dist: redis (>=7.1.0,<8.0.0)
Project-URL: Homepage, https://github.com/Turall/cache-house
Project-URL: Repository, https://github.com/Turall/cache-house
